CHANGES.txt
README.txt
bootstrap.py
setup.py
include/ExtensionClass/ExtensionClass.h
include/ExtensionClass/_ExtensionClass.c
include/ExtensionClass/__init__.py
include/ExtensionClass/tests.py
include/ExtensionClass/pickle/pickle.c
src/ThreadLock/_ThreadLock.c
src/ThreadLock/__init__.py
src/ThreadLock/tests.py
src/ThreadLock.egg-info/PKG-INFO
src/ThreadLock.egg-info/SOURCES.txt
src/ThreadLock.egg-info/dependency_links.txt
src/ThreadLock.egg-info/not-zip-safe
src/ThreadLock.egg-info/requires.txt
src/ThreadLock.egg-info/top_level.txt