Metadata-Version: 1.0
Name: ThreadLock
Version: 2.13.0
Summary: Special ThreadLock objects used in Zope2.
Home-page: http://pypi.python.org/pypi/ThreadLock
Author: Zope Corporation and Contributors
Author-email: zope-dev@zope.org
License: ZPL 2.1
Platform: UNKNOWN
